.coveragerc
.gitignore
LICENSE
PKGBUILD
Pipfile
Pipfile.lock
README.md
config_sample.ini
pyproject.toml
setup.py
tests/__init__.py
tests/conftest.py
tests/test_deezer.py
tests/test_spotify.py
tests/test_tag.py
tests/test_ydl.py
tests/test_ypc.py
tests/test_files/deezer_urls.txt
tests/test_files/search_terms.txt
tests/test_files/spotify_urls.txt
tests/test_files/youtube_urls.txt
ypc/__init__.py
ypc/__main__.py
ypc/deezer_utils.py
ypc/spotify_utils.py
ypc/tag_utils.py
ypc/ydl_utils.py
ypc.egg-info/PKG-INFO
ypc.egg-info/SOURCES.txt
ypc.egg-info/dependency_links.txt
ypc.egg-info/entry_points.txt
ypc.egg-info/requires.txt
ypc.egg-info/top_level.txt