Metadata-Version: 2.1
Name: ypc
Version: 1.7.2
Summary: Convert spotify/deezer/text playlists to youtube urls or audio/video files
Home-page: https://github.com/dbeley/ypc
Author: dbeley
Author-email: dbeley@protonmail.com
License: UNKNOWN
Platform: UNKNOWN
Classifier: Programming Language :: Python :: 3
Classifier: Operating System :: POSIX :: Linux
